soniox/__init__.py
soniox/async_client.py
soniox/cli.py
soniox/client.py
soniox/config.py
soniox/errors.py
soniox/realtime.py
soniox/types.py
soniox/utils.py
soniox_pro_sdk-1.2.0.dist-info/METADATA
soniox_pro_sdk-1.2.0.dist-info/WHEEL
soniox_pro_sdk-1.2.0.dist-info/entry_points.txt
soniox_pro_sdk-1.2.0.dist-info/licenses/LICENSE
soniox_pro_sdk-1.2.0.dist-info/RECORD
