Metadata-Version: 2.4
Name: soniox-pro-sdk
Version: 1.2.0
Summary: Professional Python SDK for Soniox Speech-to-Text API - Blazing fast, production-ready, and fully-featured
Project-URL: Homepage, https://github.com/CodeWithBehnam/soniox-pro-sdk
Project-URL: Documentation, https://codewithbehnam.github.io/soniox-pro-sdk
Project-URL: Repository, https://github.com/CodeWithBehnam/soniox-pro-sdk
Project-URL: Bug Tracker, https://github.com/CodeWithBehnam/soniox-pro-sdk/issues
Author-email: Behnam Ebrahimi <behnam@example.com>
License: MIT
License-File: LICENSE
Keywords: async,real-time,soniox,speech-to-text,stt,transcription,translation,websocket
Classifier: Development Status :: 5 - Production/Stable
Classifier: Intended Audience :: Developers
Classifier: License :: OSI Approved :: MIT License
Classifier: Programming Language :: Python :: 3
Classifier: Programming Language :: Python :: 3.12
Classifier: Programming Language :: Python :: 3.13
Classifier: Programming Language :: Python :: Implementation :: CPython
Classifier: Topic :: Multimedia :: Sound/Audio :: Speech
Classifier: Topic :: Scientific/Engineering :: Artificial Intelligence
Classifier: Topic :: Software Development :: Libraries :: Python Modules
Classifier: Typing :: Typed
Requires-Python: >=3.12
Requires-Dist: httpx[http2]>=0.27.0
Requires-Dist: pydantic>=2.0.0
Requires-Dist: python-dotenv>=1.0.0
Requires-Dist: typing-extensions>=4.10.0; python_version < '3.13'
Requires-Dist: websockets>=13.0
Provides-Extra: all
Requires-Dist: aiohttp>=3.10.0; extra == 'all'
Requires-Dist: bandit[toml]>=1.7.0; extra == 'all'
Requires-Dist: black>=24.0.0; extra == 'all'
Requires-Dist: cython>=3.0.0; extra == 'all'
Requires-Dist: detect-secrets>=1.4.0; extra == 'all'
Requires-Dist: isort>=5.13.0; extra == 'all'
Requires-Dist: mkdocs-material>=9.5.0; extra == 'all'
Requires-Dist: mkdocs>=1.5.0; extra == 'all'
Requires-Dist: mkdocstrings[python]>=0.24.0; extra == 'all'
Requires-Dist: mypy>=1.8.0; extra == 'all'
Requires-Dist: numpy>=1.26.0; extra == 'all'
Requires-Dist: pre-commit>=3.6.0; extra == 'all'
Requires-Dist: pytest-asyncio>=0.23.0; extra == 'all'
Requires-Dist: pytest-cov>=4.1.0; extra == 'all'
Requires-Dist: pytest-mock>=3.12.0; extra == 'all'
Requires-Dist: pytest>=8.0.0; extra == 'all'
Requires-Dist: ruff>=0.2.0; extra == 'all'
Provides-Extra: async
Requires-Dist: aiohttp>=3.10.0; extra == 'async'
Provides-Extra: dev
Requires-Dist: bandit[toml]>=1.7.0; extra == 'dev'
Requires-Dist: black>=24.0.0; extra == 'dev'
Requires-Dist: detect-secrets>=1.4.0; extra == 'dev'
Requires-Dist: isort>=5.13.0; extra == 'dev'
Requires-Dist: mypy>=1.8.0; extra == 'dev'
Requires-Dist: pre-commit>=3.6.0; extra == 'dev'
Requires-Dist: pytest-asyncio>=0.23.0; extra == 'dev'
Requires-Dist: pytest-cov>=4.1.0; extra == 'dev'
Requires-Dist: pytest-mock>=3.12.0; extra == 'dev'
Requires-Dist: pytest>=8.0.0; extra == 'dev'
Requires-Dist: ruff>=0.2.0; extra == 'dev'
Provides-Extra: docs
Requires-Dist: mkdocs-material>=9.5.0; extra == 'docs'
Requires-Dist: mkdocs>=1.5.0; extra == 'docs'
Requires-Dist: mkdocstrings[python]>=0.24.0; extra == 'docs'
Provides-Extra: performance
Requires-Dist: cython>=3.0.0; extra == 'performance'
Requires-Dist: numpy>=1.26.0; extra == 'performance'
